LICENSE
README.md
setup.py
src/wetsuite.egg-info/PKG-INFO
src/wetsuite.egg-info/SOURCES.txt
src/wetsuite.egg-info/dependency_links.txt
src/wetsuite.egg-info/requires.txt
src/wetsuite.egg-info/top_level.txt
src/wetsuite/datacollect/__init__.py
src/wetsuite/datacollect/eurlex.py
src/wetsuite/datacollect/koop_frbr.py
src/wetsuite/datacollect/koop_sru.py
src/wetsuite/datacollect/rechtspraaknl.py
src/wetsuite/datacollect/rijksoverheid_nl_documenten.py
src/wetsuite/datacollect/sru.py
src/wetsuite/datacollect/tweedekamer_nl.py
src/wetsuite/datasets/__init__.py
src/wetsuite/extras/__init__.py
src/wetsuite/extras/gerechtcodes.py
src/wetsuite/extras/lawref.py
src/wetsuite/extras/ocr.py
src/wetsuite/extras/pdf.py
src/wetsuite/extras/word_cloud.py
src/wetsuite/helpers/__init__.py
src/wetsuite/helpers/akn.py
src/wetsuite/helpers/collocation.py
src/wetsuite/helpers/date.py
src/wetsuite/helpers/escape.py
src/wetsuite/helpers/etree.py
src/wetsuite/helpers/format.py
src/wetsuite/helpers/koop_parse.py
src/wetsuite/helpers/lazy.py
src/wetsuite/helpers/localdata.py
src/wetsuite/helpers/meta.py
src/wetsuite/helpers/net.py
src/wetsuite/helpers/notebook.py
src/wetsuite/helpers/patterns.py
src/wetsuite/helpers/shellcolor.py
src/wetsuite/helpers/spacy.py
src/wetsuite/helpers/split.py
src/wetsuite/helpers/strings.py
src/wetsuite/helpers/util.py